XBNet/Seq.py
XBNet/__init__.py
XBNet/main.py
XBNet/models.py
XBNet/run.py
XBNet/training_utils.py
XBNet-1.4.6.dist-info/License.txt
XBNet-1.4.6.dist-info/METADATA
XBNet-1.4.6.dist-info/WHEEL
XBNet-1.4.6.dist-info/top_level.txt
XBNet-1.4.6.dist-info/RECORD
