Metadata-Version: 2.1
Name: XBNet
Version: 1.4.6
Summary: XBNet is an open source project which is built with PyTorch that works as a Boosted neural network for tabular data
Home-page: https://github.com/tusharsarkar3/
Author: Tushar Sarkar
Author-email: tushar.sarkar@somaiya.edu
License: MIT
Platform: UNKNOWN
Classifier: Programming Language :: Python :: 3
Classifier: License :: OSI Approved :: MIT License
Classifier: Operating System :: OS Independent
Requires-Dist: sklearn (==0.0)
Requires-Dist: numpy (==1.21.2)
Requires-Dist: pandas (==1.3.3)
Requires-Dist: matplotlib (==3.4.3)
Requires-Dist: torch (==1.9.0)
Requires-Dist: xgboost (==1.4.2)
Requires-Dist: tqdm (==4.62.2)
